codeformer/__init__.py
codeformer/app.py
codeformer/cli.py
codeformer/inference_codeformer.py
codeformer/basicsr/__init__.py
codeformer/basicsr/setup.py
codeformer/basicsr/train.py
codeformer/basicsr/archs/__init__.py
codeformer/basicsr/archs/arcface_arch.py
codeformer/basicsr/archs/arch_util.py
codeformer/basicsr/archs/codeformer_arch.py
codeformer/basicsr/archs/rrdbnet_arch.py
codeformer/basicsr/archs/vgg_arch.py
codeformer/basicsr/archs/vqgan_arch.py
codeformer/basicsr/data/__init__.py
codeformer/basicsr/data/data_sampler.py
codeformer/basicsr/data/data_util.py
codeformer/basicsr/data/prefetch_dataloader.py
codeformer/basicsr/data/transforms.py
codeformer/basicsr/losses/__init__.py
codeformer/basicsr/losses/loss_util.py
codeformer/basicsr/losses/losses.py
codeformer/basicsr/metrics/__init__.py
codeformer/basicsr/metrics/metric_util.py
codeformer/basicsr/metrics/psnr_ssim.py
codeformer/basicsr/models/__init__.py
codeformer/basicsr/ops/__init__.py
codeformer/basicsr/ops/dcn/__init__.py
codeformer/basicsr/ops/dcn/deform_conv.py
codeformer/basicsr/ops/fused_act/__init__.py
codeformer/basicsr/ops/fused_act/fused_act.py
codeformer/basicsr/ops/upfirdn2d/__init__.py
codeformer/basicsr/ops/upfirdn2d/upfirdn2d.py
codeformer/basicsr/utils/__init__.py
codeformer/basicsr/utils/dist_util.py
codeformer/basicsr/utils/download_util.py
codeformer/basicsr/utils/file_client.py
codeformer/basicsr/utils/img_util.py
codeformer/basicsr/utils/lmdb_util.py
codeformer/basicsr/utils/logger.py
codeformer/basicsr/utils/matlab_functions.py
codeformer/basicsr/utils/misc.py
codeformer/basicsr/utils/options.py
codeformer/basicsr/utils/realesrgan_utils.py
codeformer/basicsr/utils/registry.py
codeformer/basicsr/utils/video_util.py
codeformer/facelib/__init__.py
codeformer/facelib/detection/__init__.py
codeformer/facelib/detection/align_trans.py
codeformer/facelib/detection/matlab_cp2tform.py
codeformer/facelib/detection/retinaface/__init__.py
codeformer/facelib/detection/retinaface/retinaface.py
codeformer_cr-0.0.2.dist-info/METADATA
codeformer_cr-0.0.2.dist-info/WHEEL
codeformer_cr-0.0.2.dist-info/entry_points.txt
codeformer_cr-0.0.2.dist-info/top_level.txt
codeformer_cr-0.0.2.dist-info/RECORD
