Metadata-Version: 2.4
Name: codeformer-cr
Version: 0.0.2
Summary: PyTorch implementation of CodeFormer
Home-page: https://github.com/classronin/codeformer-cr
Author: classronin
License: S-Lab
Keywords: pytorch,codeformer,face,face-swap,face-swapping,face-swap-pytorch,face-swapping-pytorch
Classifier: Development Status :: 4 - Beta
Classifier: Operating System :: OS Independent
Classifier: Intended Audience :: Developers
Classifier: Intended Audience :: Science/Research
Classifier: Programming Language :: Python :: 3
Classifier: Programming Language :: Python :: 3.7
Classifier: Programming Language :: Python :: 3.8
Classifier: Programming Language :: Python :: 3.9
Classifier: Topic :: Software Development :: Libraries
Classifier: Topic :: Software Development :: Libraries :: Python Modules
Classifier: Topic :: Education
Classifier: Topic :: Scientific/Engineering
Classifier: Topic :: Scientific/Engineering :: Artificial Intelligence
Requires-Python: >=3.6
Requires-Dist: addict
Requires-Dist: future
Requires-Dist: lmdb
Requires-Dist: numpy
Requires-Dist: opencv-python
Requires-Dist: Pillow
Requires-Dist: pyyaml
Requires-Dist: requests
Requires-Dist: scikit-image
Requires-Dist: scipy
Requires-Dist: tb-nightly
Requires-Dist: torch>=1.7.1
Requires-Dist: torchvision
Requires-Dist: tqdm
Requires-Dist: yapf
Requires-Dist: lpips
Requires-Dist: gdown
Dynamic: author
Dynamic: classifier
Dynamic: description
Dynamic: description-content-type
Dynamic: home-page
Dynamic: keywords
Dynamic: license
Dynamic: requires-dist
Dynamic: requires-python
Dynamic: summary
